<Properties GitUserInfo="UsingGIT" StartupConfiguration="{FDA6D073-767A-4273-9299-E5DACDEAFE79}|Default">
  <MonoDevelop.Ide.Workspace ActiveConfiguration="Debug" />
  <MonoDevelop.Ide.Workbench>
    <Pads>
      <Pad Id="ProjectPad">
        <State name="__root__">
          <Node name="PRY20220278" expanded="True">
            <Node name="PRY20220278" expanded="True" selected="True" />
          </Node>
        </State>
      </Pad>
    </Pads>
  </MonoDevelop.Ide.Workbench>
  <MonoDevelop.Ide.DebuggingService.Breakpoints>
    <BreakpointStore />
  </MonoDevelop.Ide.DebuggingService.Breakpoints>
  <MultiItemStartupConfigurations />
  <MonoDevelop.Ide.ItemProperties.PRY20220278 PreferredExecutionTarget="/Applications/Safari.app" />
  <MonoDevelop.Ide.DebuggingService.PinnedWatches />
</Properties>